setup.cfg
setup.py
examples/__init__.py
examples/bus_events.py
examples/bus_simple.py
tests/channels/__init__.py
tests/events/__init__.py
tests/events/test_events.py
tests/gateway/__init__.py
voom/__init__.py
voom/bus.py
voom/context.py
voom/decorators.py
voom/exceptions.py
voom/priorities.py
voom.egg-info/PKG-INFO
voom.egg-info/SOURCES.txt
voom.egg-info/dependency_links.txt
voom.egg-info/top_level.txt
voom/adaptors/__init__.py
voom/adaptors/django/__init__.py
voom/adaptors/django/discover.py
voom/events/__init__.py
voom/events/base.py
voom/local/__init__.py