Metadata-Version: 1.1
Name: voom
Version: 2.0.1
Summary: A python message bus that you can put 4 million volts through.
Home-page: https://github.com/ninowalker/voom
Author: Nino Walker
Author-email: nino.walker@gmail.com
License: BSD
Platform: UNKNOWN
Classifier: License :: OSI Approved :: BSD License
